dynaflow/__init__.py
dynaflow/cli.py
dynaflow/model_registry.py
dynaflow/tracking_store.py
dynaflow-0.0.3a0.dist-info/entry_points.txt
dynaflow-0.0.3a0.dist-info/LICENSE
dynaflow-0.0.3a0.dist-info/WHEEL
dynaflow-0.0.3a0.dist-info/METADATA
dynaflow-0.0.3a0.dist-info/RECORD
