Metadata-Version: 2.1
Name: dynaflow
Version: 0.0.3a0
Summary: AWS Dynamodb backend tracking store for MLFlow
Home-page: https://github.com/ArrichM/dynaflow
License: Apache-2.0
Keywords: mlflow,dynamodb,tracking,mlops,aws
Author: ArrichM
Author-email: maximilianjakob.arrich@student.unisg.ch
Requires-Python: >=3.7,<4.0
Classifier: License :: OSI Approved :: Apache Software License
Classifier: Programming Language :: Python :: 3
Classifier: Programming Language :: Python :: 3.10
Classifier: Programming Language :: Python :: 3.7
Classifier: Programming Language :: Python :: 3.8
Classifier: Programming Language :: Python :: 3.9
Requires-Dist: click (>=8.0.4,<9.0.0)
Requires-Dist: mlflow (>=1.24.0,<2.0.0)
Requires-Dist: pynamodb (>=5.2.1,<6.0.0)
Project-URL: Repository, https://github.com/ArrichM/dynaflow
